odoo/addons/apikey_scope_editable/README.rst
odoo/addons/apikey_scope_editable/__init__.py
odoo/addons/apikey_scope_editable/__manifest__.py
odoo/addons/apikey_scope_editable/i18n/apikey_scope_editable.pot
odoo/addons/apikey_scope_editable/i18n/it.po
odoo/addons/apikey_scope_editable/models/__init__.py
odoo/addons/apikey_scope_editable/models/res_users_apikeys.py
odoo/addons/apikey_scope_editable/readme/CONTRIBUTORS.md
odoo/addons/apikey_scope_editable/readme/DESCRIPTION.md
odoo/addons/apikey_scope_editable/readme/USAGE.md
odoo/addons/apikey_scope_editable/static/description/icon.png
odoo/addons/apikey_scope_editable/static/description/icon.svg
odoo/addons/apikey_scope_editable/static/description/index.html
odoo/addons/apikey_scope_editable/tests/__init__.py
odoo/addons/apikey_scope_editable/tests/test_apikey_scope_editable.py
odoo/addons/apikey_scope_editable/wizards/__init__.py
odoo/addons/apikey_scope_editable/wizards/res_users_apikeys_description.py
odoo/addons/apikey_scope_editable/wizards/res_users_apikeys_description_views.xml
odoo_addon_apikey_scope_editable-17.0.1.0.0.4.dist-info/METADATA
odoo_addon_apikey_scope_editable-17.0.1.0.0.4.dist-info/WHEEL
odoo_addon_apikey_scope_editable-17.0.1.0.0.4.dist-info/top_level.txt
odoo_addon_apikey_scope_editable-17.0.1.0.0.4.dist-info/RECORD
